.gitignore
.travis.yml
setup.py
bibutils/__init__.py
bibutils/wrapper.py
bibutils.egg-info/PKG-INFO
bibutils.egg-info/SOURCES.txt
bibutils.egg-info/dependency_links.txt
bibutils.egg-info/pbr.json
bibutils.egg-info/requires.txt
bibutils.egg-info/top_level.txt
tests/__init__.py
tests/test_taalman.py
tests/test_version.py
tests/data/samples/README
tests/data/samples/taalman/database.bib