Metadata-Version: 1.1
Name: bibutils
Version: 0.0.1
Summary: bibutils wrapper.
Home-page: https://github.com/jayvdb/bibutils
Author: John Vandenberg
Author-email: jayvdb@gmail.com
License: MIT
Keywords: b,i,b, ,x,m,l, ,c,o,p,a,c, ,e,n,d, ,i,s,i, ,m,e,d, ,r,i,s, ,m,o,d,s
Platform: UNKNOWN
Classifier: Development Status :: 3 - Alpha
Classifier: Environment :: Console
Classifier: License :: OSI Approved :: MIT License
Classifier: Operating System :: OS Independent
Classifier: Programming Language :: Python
Classifier: Programming Language :: Python :: 2
Classifier: Programming Language :: Python :: 3
Classifier: Topic :: Software Development :: Libraries :: Python Modules
